setup.py
pgh_bustime.egg-info/PKG-INFO
pgh_bustime.egg-info/SOURCES.txt
pgh_bustime.egg-info/dependency_links.txt
pgh_bustime.egg-info/requires.txt
pgh_bustime.egg-info/top_level.txt
pghbustime/__init__.py
pghbustime/datatypes.py
pghbustime/interface.py
pghbustime/utils.py