Metadata-Version: 1.0
Name: pgh-bustime
Version: 0.8.0
Summary: Python wrapper for the Port Authority of Allegheny County realtime bus information API.
Home-page: http://github.com/nhfruchter/pgh-bustime
Author: Nathaniel Fruchter
Author-email: pghbustime@gmail.com
License: LICENSE
Platform: UNKNOWN
